{"name":"AlgoWiki - Best Sources at one Place!","tagline":"Repository which contains all the links and resources on different topics of Computer Science","body":"Books\r\n-----\r\n* [A Tutorial on Pointers and Arrays in C](http://home.netcom.com/~tjensen/ptr/pointers.htm)\r\n* [Advanced Linux Programming](http://www.advancedlinuxprogramming.com/)\r\n* [Beej's Guide to C Programming](http://beej.us/guide/bgc/)\r\n* [Beej's Guide to Network Programming](http://beej.us/guide/bgnet/)\r\n* [Build Your Own Lisp](http://www.buildyourownlisp.com/)\r\n* [C Programming - Wikibooks](http://en.wikibooks.org/wiki/Programming%3AC)\r\n* [Deep C](http://www.slideshare.net/olvemaudal/deep-c)\r\n* [Essential C](http://cslibrary.stanford.edu/101/EssentialC.pdf)\r\n* [Learn C the hard way](http://c.learncodethehardway.org/book/)\r\n* [Object Oriented Programming in C](http://www.planetpdf.com/codecuts/pdfs/ooc.pdf)\r\n* [The C book](http://publications.gbdirect.co.uk/c_book/)\r\n* [The Craft of Text Editing or A Cookbook for an Emacs](http://www.finseth.com/craft/) \r\n* [The GNU C Programming Tutorial](http://www.crasseux.com/books/ctut.pdf)\r\n* [The New C Standard - An Annotated Reference](http://www.knosof.co.uk/cbook/cbook.html)\r\n* [TONC GBA Programming - Game Boy Advance Development](http://www.coranac.com/tonc/text/toc.htm)\r\n* [Using C on the UNIX System - David A. Curry](http://www.bitsinthewind.com/about-dac/publications/using-c-on-the-unix-system)\r\n\r\nWebsites\r\n-------\r\nWill be updated soon!","google":"UA-45497633-6","note":"Don't delete this file! It's used internally to help with page regeneration."}